byte_harmony
