Metadata-Version: 2.1
Name: byte_harmony
Version: 0.1.5
Summary: Python love and robots
Home-page: https://radioframenetworks.com/jacknote
Author: jdev
Author-email: jdev@radioframenetworks.com
